{
  "Model": 0,
  "Textures": null,
  "Textures2": null,
  "TextureFiles": {
    "27757": [
      {
        "FileDataId": 152017,
        "Gender": 1,
        "Class": 0,
        "Race": 0,
        "ExtraData": 0
      },
      {
        "FileDataId": 152018,
        "Gender": 0,
        "Class": 0,
        "Race": 0,
        "ExtraData": 0
      }
    ],
    "44077": [
      {
        "FileDataId": 164143,
        "Gender": 1,
        "Class": 0,
        "Race": 0,
        "ExtraData": 0
      },
      {
        "FileDataId": 164144,
        "Gender": 0,
        "Class": 0,
        "Race": 0,
        "ExtraData": 0
      }
    ],
    "45904": [
      {
        "FileDataId": 161463,
        "Gender": 1,
        "Class": 0,
        "Race": 0,
        "ExtraData": 0
      },
      {
        "FileDataId": 161464,
        "Gender": 0,
        "Class": 0,
        "Race": 0,
        "ExtraData": 0
      }
    ]
  },
  "ModelFiles": null,
  "Item": {
    "Flags": 0,
    "InventoryType": 5,
    "ItemClass": 4,
    "ItemSubClass": 3,
    "HideGeosetMale": null,
    "HideGeosetFemale": null,
    "GeosetGroup": [
      0,
      0,
      0,
      0,
      0,
      0
    ],
    "AttachGeosetGroup": [
      0,
      0,
      0,
      0,
      0,
      0
    ],
    "GeosetGroupOverride": 0,
    "ItemVisual": 0,
    "ParticleColor": null
  },
  "Creature": null,
  "Character": null,
  "ItemEffects": null,
  "Equipment": null,
  "ComponentTextures": {
    "0": 27757,
    "3": 44077,
    "4": 45904
  },
  "ComponentModels": null,
  "StateKit": null,
  "StateKits": null,
  "Scale": 1
}