{
  "Model": 0,
  "Textures": {
    "2": 143846
  },
  "Textures2": {
    "2": 143846
  },
  "TextureFiles": null,
  "ModelFiles": {
    "16079": [
      {
        "FileDataId": 143189,
        "Gender": 2,
        "Class": 0,
        "Race": 0,
        "ExtraData": 0
      },
      {
        "FileDataId": 143492,
        "Gender": 2,
        "Class": 0,
        "Race": 0,
        "ExtraData": 1
      }
    ]
  },
  "Item": {
    "Flags": 0,
    "InventoryType": 3,
    "ItemClass": 0,
    "ItemSubClass": 0,
    "HideGeosetMale": null,
    "HideGeosetFemale": null,
    "GeosetGroup": [
      0,
      0,
      0,
      0,
      0,
      0
    ],
    "AttachGeosetGroup": [
      0,
      0,
      0,
      0,
      0,
      0
    ],
    "GeosetGroupOverride": 0,
    "ItemVisual": 0,
    "ParticleColor": {
      "Id": 354,
      "Start": [
        0,
        0,
        0
      ],
      "Mid": [
        0,
        0,
        0
      ],
      "End": [
        0,
        0,
        0
      ]
    }
  },
  "Creature": null,
  "Character": null,
  "ItemEffects": null,
  "Equipment": null,
  "ComponentTextures": null,
  "ComponentModels": {
    "0": 16079,
    "1": 16079
  },
  "StateKit": null,
  "StateKits": null,
  "Scale": 1
}