{
  "Model": 0,
  "Textures": {
    "2": 140917
  },
  "Textures2": null,
  "TextureFiles": null,
  "ModelFiles": {
    "17370": [
      {
        "FileDataId": 140893,
        "Gender": 1,
        "Class": 0,
        "Race": 10,
        "ExtraData": -1
      },
      {
        "FileDataId": 140894,
        "Gender": 0,
        "Class": 0,
        "Race": 10,
        "ExtraData": -1
      },
      {
        "FileDataId": 140895,
        "Gender": 1,
        "Class": 0,
        "Race": 11,
        "ExtraData": -1
      },
      {
        "FileDataId": 140896,
        "Gender": 0,
        "Class": 0,
        "Race": 11,
        "ExtraData": -1
      },
      {
        "FileDataId": 140897,
        "Gender": 1,
        "Class": 0,
        "Race": 3,
        "ExtraData": -1
      },
      {
        "FileDataId": 140898,
        "Gender": 0,
        "Class": 0,
        "Race": 3,
        "ExtraData": -1
      },
      {
        "FileDataId": 140899,
        "Gender": 1,
        "Class": 0,
        "Race": 7,
        "ExtraData": -1
      },
      {
        "FileDataId": 140900,
        "Gender": 0,
        "Class": 0,
        "Race": 7,
        "ExtraData": -1
      },
      {
        "FileDataId": 140901,
        "Gender": 1,
        "Class": 0,
        "Race": 9,
        "ExtraData": -1
      },
      {
        "FileDataId": 140902,
        "Gender": 1,
        "Class": 0,
        "Race": 1,
        "ExtraData": -1
      },
      {
        "FileDataId": 140903,
        "Gender": 0,
        "Class": 0,
        "Race": 1,
        "ExtraData": -1
      },
      {
        "FileDataId": 140904,
        "Gender": 1,
        "Class": 0,
        "Race": 4,
        "ExtraData": -1
      },
      {
        "FileDataId": 140905,
        "Gender": 0,
        "Class": 0,
        "Race": 4,
        "ExtraData": -1
      },
      {
        "FileDataId": 140906,
        "Gender": 1,
        "Class": 0,
        "Race": 2,
        "ExtraData": -1
      },
      {
        "FileDataId": 140907,
        "Gender": 0,
        "Class": 0,
        "Race": 2,
        "ExtraData": -1
      },
      {
        "FileDataId": 140908,
        "Gender": 1,
        "Class": 0,
        "Race": 5,
        "ExtraData": -1
      },
      {
        "FileDataId": 140909,
        "Gender": 0,
        "Class": 0,
        "Race": 5,
        "ExtraData": -1
      },
      {
        "FileDataId": 140910,
        "Gender": 1,
        "Class": 0,
        "Race": 6,
        "ExtraData": -1
      },
      {
        "FileDataId": 140911,
        "Gender": 0,
        "Class": 0,
        "Race": 6,
        "ExtraData": -1
      },
      {
        "FileDataId": 140912,
        "Gender": 1,
        "Class": 0,
        "Race": 8,
        "ExtraData": -1
      },
      {
        "FileDataId": 140913,
        "Gender": 0,
        "Class": 0,
        "Race": 8,
        "ExtraData": -1
      }
    ]
  },
  "Item": {
    "Flags": 0,
    "InventoryType": 1,
    "ItemClass": 0,
    "ItemSubClass": 0,
    "HideGeosetMale": [
      {
        "RaceId": 1,
        "GeosetGroup": 0,
        "RaceBitSelection": 0
      },
      {
        "RaceId": 2,
        "GeosetGroup": 0,
        "RaceBitSelection": 0
      },
      {
        "RaceId": 3,
        "GeosetGroup": 0,
        "RaceBitSelection": 0
      },
      {
        "RaceId": 4,
        "GeosetGroup": 0,
        "RaceBitSelection": 0
      },
      {
        "RaceId": 5,
        "GeosetGroup": 0,
        "RaceBitSelection": 0
      },
      {
        "RaceId": 7,
        "GeosetGroup": 0,
        "RaceBitSelection": 0
      },
      {
        "RaceId": 8,
        "GeosetGroup": 0,
        "RaceBitSelection": 0
      },
      {
        "RaceId": 9,
        "GeosetGroup": 0,
        "RaceBitSelection": 0
      },
      {
        "RaceId": 10,
        "GeosetGroup": 0,
        "RaceBitSelection": 0
      },
      {
        "RaceId": 11,
        "GeosetGroup": 0,
        "RaceBitSelection": 0
      },
      {
        "RaceId": 12,
        "GeosetGroup": 0,
        "RaceBitSelection": 0
      },
      {
        "RaceId": 13,
        "GeosetGroup": 0,
        "RaceBitSelection": 0
      },
      {
        "RaceId": 14,
        "GeosetGroup": 0,
        "RaceBitSelection": 0
      },
      {
        "RaceId": 15,
        "GeosetGroup": 0,
        "RaceBitSelection": 0
      },
      {
        "RaceId": 18,
        "GeosetGroup": 0,
        "RaceBitSelection": 0
      },
      {
        "RaceId": 1,
        "GeosetGroup": 1,
        "RaceBitSelection": 0
      },
      {
        "RaceId": 2,
        "GeosetGroup": 1,
        "RaceBitSelection": 0
      },
      {
        "RaceId": 3,
        "GeosetGroup": 1,
        "RaceBitSelection": 0
      },
      {
        "RaceId": 4,
        "GeosetGroup": 1,
        "RaceBitSelection": 0
      },
      {
        "RaceId": 6,
        "GeosetGroup": 1,
        "RaceBitSelection": 0
      },
      {
        "RaceId": 7,
        "GeosetGroup": 1,
        "RaceBitSelection": 0
      },
      {
        "RaceId": 8,
        "GeosetGroup": 1,
        "RaceBitSelection": 0
      },
      {
        "RaceId": 9,
        "GeosetGroup": 1,
        "RaceBitSelection": 0
      },
      {
        "RaceId": 10,
        "GeosetGroup": 1,
        "RaceBitSelection": 0
      },
      {
        "RaceId": 11,
        "GeosetGroup": 1,
        "RaceBitSelection": 0
      },
      {
        "RaceId": 12,
        "GeosetGroup": 1,
        "RaceBitSelection": 0
      },
      {
        "RaceId": 13,
        "GeosetGroup": 1,
        "RaceBitSelection": 0
      },
      {
        "RaceId": 14,
        "GeosetGroup": 1,
        "RaceBitSelection": 0
      },
      {
        "RaceId": 15,
        "GeosetGroup": 1,
        "RaceBitSelection": 0
      },
      {
        "RaceId": 18,
        "GeosetGroup": 1,
        "RaceBitSelection": 0
      },
      {
        "RaceId": 1,
        "GeosetGroup": 2,
        "RaceBitSelection": 0
      },
      {
        "RaceId": 2,
        "GeosetGroup": 2,
        "RaceBitSelection": 0
      },
      {
        "RaceId": 3,
        "GeosetGroup": 2,
        "RaceBitSelection": 0
      },
      {
        "RaceId": 4,
        "GeosetGroup": 2,
        "RaceBitSelection": 0
      },
      {
        "RaceId": 5,
        "GeosetGroup": 2,
        "RaceBitSelection": 0
      },
      {
        "RaceId": 7,
        "GeosetGroup": 2,
        "RaceBitSelection": 0
      },
      {
        "RaceId": 8,
        "GeosetGroup": 2,
        "RaceBitSelection": 0
      },
      {
        "RaceId": 9,
        "GeosetGroup": 2,
        "RaceBitSelection": 0
      },
      {
        "RaceId": 10,
        "GeosetGroup": 2,
        "RaceBitSelection": 0
      },
      {
        "RaceId": 11,
        "GeosetGroup": 2,
        "RaceBitSelection": 0
      },
      {
        "RaceId": 12,
        "GeosetGroup": 2,
        "RaceBitSelection": 0
      },
      {
        "RaceId": 13,
        "GeosetGroup": 2,
        "RaceBitSelection": 0
      },
      {
        "RaceId": 14,
        "GeosetGroup": 2,
        "RaceBitSelection": 0
      },
      {
        "RaceId": 15,
        "GeosetGroup": 2,
        "RaceBitSelection": 0
      },
      {
        "RaceId": 18,
        "GeosetGroup": 2,
        "RaceBitSelection": 0
      },
      {
        "RaceId": 1,
        "GeosetGroup": 3,
        "RaceBitSelection": 0
      },
      {
        "RaceId": 2,
        "GeosetGroup": 3,
        "RaceBitSelection": 0
      },
      {
        "RaceId": 3,
        "GeosetGroup": 3,
        "RaceBitSelection": 0
      },
      {
        "RaceId": 4,
        "GeosetGroup": 3,
        "RaceBitSelection": 0
      },
      {
        "RaceId": 6,
        "GeosetGroup": 3,
        "RaceBitSelection": 0
      },
      {
        "RaceId": 7,
        "GeosetGroup": 3,
        "RaceBitSelection": 0
      },
      {
        "RaceId": 9,
        "GeosetGroup": 3,
        "RaceBitSelection": 0
      },
      {
        "RaceId": 10,
        "GeosetGroup": 3,
        "RaceBitSelection": 0
      },
      {
        "RaceId": 11,
        "GeosetGroup": 3,
        "RaceBitSelection": 0
      },
      {
        "RaceId": 12,
        "GeosetGroup": 3,
        "RaceBitSelection": 0
      },
      {
        "RaceId": 13,
        "GeosetGroup": 3,
        "RaceBitSelection": 0
      },
      {
        "RaceId": 14,
        "GeosetGroup": 3,
        "RaceBitSelection": 0
      },
      {
        "RaceId": 15,
        "GeosetGroup": 3,
        "RaceBitSelection": 0
      },
      {
        "RaceId": 18,
        "GeosetGroup": 3,
        "RaceBitSelection": 0
      },
      {
        "RaceId": 1,
        "GeosetGroup": 7,
        "RaceBitSelection": 0
      },
      {
        "RaceId": 2,
        "GeosetGroup": 7,
        "RaceBitSelection": 0
      },
      {
        "RaceId": 3,
        "GeosetGroup": 7,
        "RaceBitSelection": 0
      },
      {
        "RaceId": 5,
        "GeosetGroup": 7,
        "RaceBitSelection": 0
      },
      {
        "RaceId": 6,
        "GeosetGroup": 7,
        "RaceBitSelection": 0
      },
      {
        "RaceId": 7,
        "GeosetGroup": 7,
        "RaceBitSelection": 0
      },
      {
        "RaceId": 9,
        "GeosetGroup": 7,
        "RaceBitSelection": 0
      },
      {
        "RaceId": 11,
        "GeosetGroup": 7,
        "RaceBitSelection": 0
      },
      {
        "RaceId": 12,
        "GeosetGroup": 7,
        "RaceBitSelection": 0
      },
      {
        "RaceId": 13,
        "GeosetGroup": 7,
        "RaceBitSelection": 0
      },
      {
        "RaceId": 14,
        "GeosetGroup": 7,
        "RaceBitSelection": 0
      },
      {
        "RaceId": 15,
        "GeosetGroup": 7,
        "RaceBitSelection": 0
      },
      {
        "RaceId": 18,
        "GeosetGroup": 7,
        "RaceBitSelection": 0
      },
      {
        "RaceId": 16,
        "GeosetGroup": 0,
        "RaceBitSelection": 0
      },
      {
        "RaceId": 17,
        "GeosetGroup": 0,
        "RaceBitSelection": 0
      },
      {
        "RaceId": 19,
        "GeosetGroup": 0,
        "RaceBitSelection": 0
      },
      {
        "RaceId": 20,
        "GeosetGroup": 0,
        "RaceBitSelection": 0
      },
      {
        "RaceId": 21,
        "GeosetGroup": 0,
        "RaceBitSelection": 0
      },
      {
        "RaceId": 16,
        "GeosetGroup": 1,
        "RaceBitSelection": 0
      },
      {
        "RaceId": 17,
        "GeosetGroup": 1,
        "RaceBitSelection": 0
      },
      {
        "RaceId": 19,
        "GeosetGroup": 1,
        "RaceBitSelection": 0
      },
      {
        "RaceId": 20,
        "GeosetGroup": 1,
        "RaceBitSelection": 0
      },
      {
        "RaceId": 21,
        "GeosetGroup": 1,
        "RaceBitSelection": 0
      },
      {
        "RaceId": 16,
        "GeosetGroup": 2,
        "RaceBitSelection": 0
      },
      {
        "RaceId": 17,
        "GeosetGroup": 2,
        "RaceBitSelection": 0
      },
      {
        "RaceId": 19,
        "GeosetGroup": 2,
        "RaceBitSelection": 0
      },
      {
        "RaceId": 20,
        "GeosetGroup": 2,
        "RaceBitSelection": 0
      },
      {
        "RaceId": 21,
        "GeosetGroup": 2,
        "RaceBitSelection": 0
      },
      {
        "RaceId": 16,
        "GeosetGroup": 3,
        "RaceBitSelection": 0
      },
      {
        "RaceId": 17,
        "GeosetGroup": 3,
        "RaceBitSelection": 0
      },
      {
        "RaceId": 19,
        "GeosetGroup": 3,
        "RaceBitSelection": 0
      },
      {
        "RaceId": 20,
        "GeosetGroup": 3,
        "RaceBitSelection": 0
      },
      {
        "RaceId": 21,
        "GeosetGroup": 3,
        "RaceBitSelection": 0
      },
      {
        "RaceId": 16,
        "GeosetGroup": 7,
        "RaceBitSelection": 0
      },
      {
        "RaceId": 17,
        "GeosetGroup": 7,
        "RaceBitSelection": 0
      },
      {
        "RaceId": 19,
        "GeosetGroup": 7,
        "RaceBitSelection": 0
      },
      {
        "RaceId": 20,
        "GeosetGroup": 7,
        "RaceBitSelection": 0
      },
      {
        "RaceId": 21,
        "GeosetGroup": 7,
        "RaceBitSelection": 0
      }
    ],
    "HideGeosetFemale": [
      {
        "RaceId": 1,
        "GeosetGroup": 0,
        "RaceBitSelection": 0
      },
      {
        "RaceId": 2,
        "GeosetGroup": 0,
        "RaceBitSelection": 0
      },
      {
        "RaceId": 3,
        "GeosetGroup": 0,
        "RaceBitSelection": 0
      },
      {
        "RaceId": 4,
        "GeosetGroup": 0,
        "RaceBitSelection": 0
      },
      {
        "RaceId": 5,
        "GeosetGroup": 0,
        "RaceBitSelection": 0
      },
      {
        "RaceId": 7,
        "GeosetGroup": 0,
        "RaceBitSelection": 0
      },
      {
        "RaceId": 8,
        "GeosetGroup": 0,
        "RaceBitSelection": 0
      },
      {
        "RaceId": 10,
        "GeosetGroup": 0,
        "RaceBitSelection": 0
      },
      {
        "RaceId": 11,
        "GeosetGroup": 0,
        "RaceBitSelection": 0
      },
      {
        "RaceId": 1,
        "GeosetGroup": 1,
        "RaceBitSelection": 0
      },
      {
        "RaceId": 2,
        "GeosetGroup": 1,
        "RaceBitSelection": 0
      },
      {
        "RaceId": 3,
        "GeosetGroup": 1,
        "RaceBitSelection": 0
      },
      {
        "RaceId": 4,
        "GeosetGroup": 1,
        "RaceBitSelection": 0
      },
      {
        "RaceId": 6,
        "GeosetGroup": 1,
        "RaceBitSelection": 0
      },
      {
        "RaceId": 7,
        "GeosetGroup": 1,
        "RaceBitSelection": 0
      },
      {
        "RaceId": 8,
        "GeosetGroup": 1,
        "RaceBitSelection": 0
      },
      {
        "RaceId": 10,
        "GeosetGroup": 1,
        "RaceBitSelection": 0
      },
      {
        "RaceId": 1,
        "GeosetGroup": 2,
        "RaceBitSelection": 0
      },
      {
        "RaceId": 2,
        "GeosetGroup": 2,
        "RaceBitSelection": 0
      },
      {
        "RaceId": 3,
        "GeosetGroup": 2,
        "RaceBitSelection": 0
      },
      {
        "RaceId": 4,
        "GeosetGroup": 2,
        "RaceBitSelection": 0
      },
      {
        "RaceId": 5,
        "GeosetGroup": 2,
        "RaceBitSelection": 0
      },
      {
        "RaceId": 6,
        "GeosetGroup": 2,
        "RaceBitSelection": 0
      },
      {
        "RaceId": 7,
        "GeosetGroup": 2,
        "RaceBitSelection": 0
      },
      {
        "RaceId": 8,
        "GeosetGroup": 2,
        "RaceBitSelection": 0
      },
      {
        "RaceId": 10,
        "GeosetGroup": 2,
        "RaceBitSelection": 0
      },
      {
        "RaceId": 1,
        "GeosetGroup": 3,
        "RaceBitSelection": 0
      },
      {
        "RaceId": 2,
        "GeosetGroup": 3,
        "RaceBitSelection": 0
      },
      {
        "RaceId": 3,
        "GeosetGroup": 3,
        "RaceBitSelection": 0
      },
      {
        "RaceId": 4,
        "GeosetGroup": 3,
        "RaceBitSelection": 0
      },
      {
        "RaceId": 6,
        "GeosetGroup": 3,
        "RaceBitSelection": 0
      },
      {
        "RaceId": 7,
        "GeosetGroup": 3,
        "RaceBitSelection": 0
      },
      {
        "RaceId": 10,
        "GeosetGroup": 3,
        "RaceBitSelection": 0
      },
      {
        "RaceId": 1,
        "GeosetGroup": 7,
        "RaceBitSelection": 0
      },
      {
        "RaceId": 2,
        "GeosetGroup": 7,
        "RaceBitSelection": 0
      },
      {
        "RaceId": 3,
        "GeosetGroup": 7,
        "RaceBitSelection": 0
      },
      {
        "RaceId": 5,
        "GeosetGroup": 7,
        "RaceBitSelection": 0
      },
      {
        "RaceId": 6,
        "GeosetGroup": 7,
        "RaceBitSelection": 0
      },
      {
        "RaceId": 7,
        "GeosetGroup": 7,
        "RaceBitSelection": 0
      },
      {
        "RaceId": 11,
        "GeosetGroup": 7,
        "RaceBitSelection": 0
      }
    ],
    "GeosetGroup": [
      0,
      0,
      0,
      0,
      0,
      0
    ],
    "AttachGeosetGroup": [
      0,
      0,
      0,
      0,
      0,
      0
    ],
    "GeosetGroupOverride": 0,
    "ItemVisual": 0,
    "ParticleColor": null
  },
  "Creature": null,
  "Character": null,
  "ItemEffects": null,
  "Equipment": null,
  "ComponentTextures": null,
  "ComponentModels": {
    "0": 17370
  },
  "StateKit": null,
  "StateKits": null,
  "Scale": 1
}