{
  "Model": 0,
  "Textures": {
    "2": 249208
  },
  "Textures2": null,
  "TextureFiles": null,
  "ModelFiles": {
    "4218": [
      {
        "FileDataId": 249185,
        "Gender": 1,
        "Class": 0,
        "Race": 10,
        "ExtraData": -1
      },
      {
        "FileDataId": 249186,
        "Gender": 0,
        "Class": 0,
        "Race": 10,
        "ExtraData": -1
      },
      {
        "FileDataId": 249187,
        "Gender": 1,
        "Class": 0,
        "Race": 11,
        "ExtraData": -1
      },
      {
        "FileDataId": 249188,
        "Gender": 0,
        "Class": 0,
        "Race": 11,
        "ExtraData": -1
      },
      {
        "FileDataId": 249189,
        "Gender": 1,
        "Class": 0,
        "Race": 3,
        "ExtraData": -1
      },
      {
        "FileDataId": 249190,
        "Gender": 0,
        "Class": 0,
        "Race": 3,
        "ExtraData": -1
      },
      {
        "FileDataId": 249191,
        "Gender": 1,
        "Class": 0,
        "Race": 7,
        "ExtraData": -1
      },
      {
        "FileDataId": 249192,
        "Gender": 0,
        "Class": 0,
        "Race": 7,
        "ExtraData": -1
      },
      {
        "FileDataId": 249193,
        "Gender": 1,
        "Class": 0,
        "Race": 9,
        "ExtraData": -1
      },
      {
        "FileDataId": 249194,
        "Gender": 0,
        "Class": 0,
        "Race": 9,
        "ExtraData": -1
      },
      {
        "FileDataId": 249195,
        "Gender": 1,
        "Class": 0,
        "Race": 1,
        "ExtraData": -1
      },
      {
        "FileDataId": 249196,
        "Gender": 0,
        "Class": 0,
        "Race": 1,
        "ExtraData": -1
      },
      {
        "FileDataId": 249197,
        "Gender": 1,
        "Class": 0,
        "Race": 4,
        "ExtraData": -1
      },
      {
        "FileDataId": 249198,
        "Gender": 0,
        "Class": 0,
        "Race": 4,
        "ExtraData": -1
      },
      {
        "FileDataId": 249199,
        "Gender": 1,
        "Class": 0,
        "Race": 2,
        "ExtraData": -1
      },
      {
        "FileDataId": 249200,
        "Gender": 0,
        "Class": 0,
        "Race": 2,
        "ExtraData": -1
      },
      {
        "FileDataId": 249201,
        "Gender": 1,
        "Class": 0,
        "Race": 5,
        "ExtraData": -1
      },
      {
        "FileDataId": 249202,
        "Gender": 0,
        "Class": 0,
        "Race": 5,
        "ExtraData": -1
      },
      {
        "FileDataId": 249203,
        "Gender": 1,
        "Class": 0,
        "Race": 6,
        "ExtraData": -1
      },
      {
        "FileDataId": 249204,
        "Gender": 0,
        "Class": 0,
        "Race": 6,
        "ExtraData": -1
      },
      {
        "FileDataId": 249205,
        "Gender": 1,
        "Class": 0,
        "Race": 8,
        "ExtraData": -1
      },
      {
        "FileDataId": 249206,
        "Gender": 0,
        "Class": 0,
        "Race": 8,
        "ExtraData": -1
      }
    ]
  },
  "Item": {
    "Flags": 0,
    "InventoryType": 1,
    "ItemClass": 4,
    "ItemSubClass": 2,
    "HideGeosetMale": null,
    "HideGeosetFemale": null,
    "GeosetGroup": [
      0,
      0,
      0,
      0,
      0,
      0
    ],
    "AttachGeosetGroup": [
      0,
      0,
      0,
      0,
      0,
      0
    ],
    "GeosetGroupOverride": 0,
    "ItemVisual": 0,
    "ParticleColor": null
  },
  "Creature": null,
  "Character": null,
  "ItemEffects": null,
  "Equipment": null,
  "ComponentTextures": null,
  "ComponentModels": {
    "0": 4218
  },
  "StateKit": null,
  "StateKits": null,
  "Scale": 1
}