{
  "Model": 0,
  "Textures": null,
  "Textures2": null,
  "TextureFiles": {
    "136177": [
      {
        "FileDataId": 346977,
        "Gender": 3,
        "Class": 0,
        "Race": 0,
        "ExtraData": 0
      }
    ]
  },
  "ModelFiles": null,
  "Item": null,
  "Creature": {
    "CreatureGeosetData": null,
    "CreatureGeosetDataID": 0,
    "CreatureModelAlpha": 255,
    "Texture": 136177,
    "CreatureCustomizations": [
      {
        "optionId": 74,
        "choiceId": 28528
      },
      {
        "optionId": 77,
        "choiceId": 17724
      },
      {
        "optionId": 78,
        "choiceId": 17726
      },
      {
        "optionId": 79,
        "choiceId": 17733
      },
      {
        "optionId": 379,
        "choiceId": 17715
      }
    ],
    "ParticleColor": null
  },
  "Character": {
    "RaceFlags": 0,
    "ChrModelFlags": 3,
    "Race": 6,
    "Gender": 1,
    "ChrModelId": 12
  },
  "ItemEffects": null,
  "Equipment": {
    "4": 23381,
    "6": 16928,
    "7": 6183,
    "8": 23382,
    "10": 9543
  },
  "ComponentTextures": null,
  "ComponentModels": null,
  "StateKit": null,
  "StateKits": null,
  "Scale": 1
}