{
  "Model": 0,
  "Textures": null,
  "Textures2": null,
  "TextureFiles": {
    "113937": [
      {
        "FileDataId": 319899,
        "Gender": 3,
        "Class": 0,
        "Race": 0,
        "ExtraData": 0
      }
    ]
  },
  "ModelFiles": null,
  "Item": null,
  "Creature": {
    "CreatureGeosetData": null,
    "CreatureGeosetDataID": 0,
    "CreatureModelAlpha": 255,
    "Texture": 113937,
    "CreatureCustomizations": [
      {
        "optionId": 25,
        "choiceId": 17329
      },
      {
        "optionId": 26,
        "choiceId": 17343
      },
      {
        "optionId": 27,
        "choiceId": 17352
      },
      {
        "optionId": 28,
        "choiceId": 17360
      },
      {
        "optionId": 29,
        "choiceId": 17368
      }
    ],
    "ParticleColor": null
  },
  "Character": {
    "RaceFlags": 0,
    "ChrModelFlags": 2,
    "Race": 2,
    "Gender": 1,
    "ChrModelId": 4
  },
  "ItemEffects": null,
  "Equipment": {
    "1": 27083,
    "3": 39543,
    "4": 57825,
    "5": 57826,
    "6": 57827,
    "7": 45932,
    "8": 39546,
    "9": 39547,
    "10": 39540
  },
  "ComponentTextures": null,
  "ComponentModels": null,
  "StateKit": null,
  "StateKits": null,
  "Scale": 1
}