{
  "Model": 0,
  "Textures": null,
  "Textures2": null,
  "TextureFiles": {
    "117093": [
      {
        "FileDataId": 570305,
        "Gender": 3,
        "Class": 0,
        "Race": 0,
        "ExtraData": 0
      }
    ]
  },
  "ModelFiles": null,
  "Item": null,
  "Creature": {
    "CreatureGeosetData": null,
    "CreatureGeosetDataID": 0,
    "CreatureModelAlpha": 255,
    "Texture": 117093,
    "CreatureCustomizations": [
      {
        "optionId": 9,
        "choiceId": 17161
      },
      {
        "optionId": 10,
        "choiceId": 17181
      },
      {
        "optionId": 11,
        "choiceId": 17192
      },
      {
        "optionId": 12,
        "choiceId": 17203
      },
      {
        "optionId": 13,
        "choiceId": 17210
      }
    ],
    "ParticleColor": null
  },
  "Character": {
    "RaceFlags": 0,
    "ChrModelFlags": 2,
    "Race": 1,
    "Gender": 0,
    "ChrModelId": 1
  },
  "ItemEffects": null,
  "Equipment": {
    "1": 5767,
    "3": 13180,
    "4": 13179,
    "6": 10501,
    "7": 10794,
    "8": 9573
  },
  "ComponentTextures": null,
  "ComponentModels": null,
  "StateKit": null,
  "StateKits": null,
  "Scale": 1
}