{
  "Model": 0,
  "Textures": null,
  "Textures2": null,
  "TextureFiles": {
    "115709": [
      {
        "FileDataId": 253574,
        "Gender": 3,
        "Class": 0,
        "Race": 0,
        "ExtraData": 0
      }
    ]
  },
  "ModelFiles": null,
  "Item": null,
  "Creature": {
    "CreatureGeosetData": null,
    "CreatureGeosetDataID": 0,
    "CreatureModelAlpha": 180,
    "Texture": 115709,
    "CreatureCustomizations": [
      {
        "optionId": 68,
        "choiceId": 28511
      },
      {
        "optionId": 71,
        "choiceId": 17692
      },
      {
        "optionId": 72,
        "choiceId": 28522
      },
      {
        "optionId": 73,
        "choiceId": 17699
      },
      {
        "optionId": 378,
        "choiceId": 17682
      }
    ],
    "ParticleColor": null
  },
  "Character": {
    "RaceFlags": 0,
    "ChrModelFlags": 3,
    "Race": 6,
    "Gender": 0,
    "ChrModelId": 11
  },
  "ItemEffects": null,
  "Equipment": {
    "5": 33490,
    "7": 33491,
    "8": 33505
  },
  "ComponentTextures": null,
  "ComponentModels": null,
  "StateKit": null,
  "StateKits": null,
  "Scale": 1
}