{
  "Model": 0,
  "Textures": null,
  "Textures2": null,
  "TextureFiles": {
    "114952": [
      {
        "FileDataId": 981115,
        "Gender": 3,
        "Class": 0,
        "Race": 0,
        "ExtraData": 0
      }
    ]
  },
  "ModelFiles": null,
  "Item": null,
  "Creature": {
    "CreatureGeosetData": null,
    "CreatureGeosetDataID": 0,
    "CreatureModelAlpha": 255,
    "Texture": 114952,
    "CreatureCustomizations": [
      {
        "optionId": 68,
        "choiceId": 17662
      },
      {
        "optionId": 71,
        "choiceId": 17686
      },
      {
        "optionId": 72,
        "choiceId": 17694
      },
      {
        "optionId": 73,
        "choiceId": 17697
      },
      {
        "optionId": 378,
        "choiceId": 17681
      }
    ],
    "ParticleColor": null
  },
  "Character": {
    "RaceFlags": 0,
    "ChrModelFlags": 3,
    "Race": 6,
    "Gender": 0,
    "ChrModelId": 11
  },
  "ItemEffects": null,
  "Equipment": {
    "1": 1127,
    "4": 10018,
    "6": 9027,
    "7": 9028,
    "8": 9029,
    "10": 11152
  },
  "ComponentTextures": null,
  "ComponentModels": null,
  "StateKit": null,
  "StateKits": null,
  "Scale": 1
}