{
  "Model": 0,
  "Textures": null,
  "Textures2": null,
  "TextureFiles": {
    "318540": [
      {
        "FileDataId": 328659,
        "Gender": 3,
        "Class": 0,
        "Race": 0,
        "ExtraData": 0
      }
    ]
  },
  "ModelFiles": null,
  "Item": null,
  "Creature": {
    "CreatureGeosetData": null,
    "CreatureGeosetDataID": 0,
    "CreatureModelAlpha": 255,
    "Texture": 318540,
    "CreatureCustomizations": [
      {
        "optionId": 100,
        "choiceId": 17899
      },
      {
        "optionId": 102,
        "choiceId": 17901
      }
    ],
    "ParticleColor": null
  },
  "Character": {
    "RaceFlags": 0,
    "ChrModelFlags": 0,
    "Race": 9,
    "Gender": 0,
    "ChrModelId": 17
  },
  "ItemEffects": null,
  "Equipment": {
    "3": 11540,
    "4": 25210,
    "6": 25311,
    "7": 5717,
    "8": 19171,
    "10": 11303
  },
  "ComponentTextures": null,
  "ComponentModels": null,
  "StateKit": null,
  "StateKits": null,
  "Scale": 1
}