{
  "Model": 0,
  "Textures": null,
  "Textures2": null,
  "TextureFiles": {
    "132162": [
      {
        "FileDataId": 1008219,
        "Gender": 3,
        "Class": 0,
        "Race": 0,
        "ExtraData": 0
      }
    ]
  },
  "ModelFiles": null,
  "Item": null,
  "Creature": {
    "CreatureGeosetData": null,
    "CreatureGeosetDataID": 0,
    "CreatureModelAlpha": 255,
    "Texture": 132162,
    "CreatureCustomizations": [
      {
        "optionId": 128,
        "choiceId": 18025
      },
      {
        "optionId": 129,
        "choiceId": 18039
      },
      {
        "optionId": 130,
        "choiceId": 18049
      },
      {
        "optionId": 131,
        "choiceId": 18058
      },
      {
        "optionId": 132,
        "choiceId": 18065
      }
    ],
    "ParticleColor": null
  },
  "Character": {
    "RaceFlags": 0,
    "ChrModelFlags": 3,
    "Race": 11,
    "Gender": 0,
    "ChrModelId": 21
  },
  "ItemEffects": null,
  "Equipment": {
    "5": 35706,
    "6": 35707,
    "7": 35708
  },
  "ComponentTextures": null,
  "ComponentModels": null,
  "StateKit": null,
  "StateKits": null,
  "Scale": 1
}