{
  "Model": 0,
  "Textures": null,
  "Textures2": null,
  "TextureFiles": {
    "172070": [
      {
        "FileDataId": 926931,
        "Gender": 3,
        "Class": 0,
        "Race": 0,
        "ExtraData": 0
      }
    ]
  },
  "ModelFiles": null,
  "Item": null,
  "Creature": {
    "CreatureGeosetData": null,
    "CreatureGeosetDataID": 0,
    "CreatureModelAlpha": 255,
    "Texture": 172070,
    "CreatureCustomizations": [
      {
        "optionId": 19,
        "choiceId": 17284
      },
      {
        "optionId": 20,
        "choiceId": 17294
      },
      {
        "optionId": 21,
        "choiceId": 17303
      },
      {
        "optionId": 22,
        "choiceId": 17314
      },
      {
        "optionId": 23,
        "choiceId": 17318
      }
    ],
    "ParticleColor": null
  },
  "Character": {
    "RaceFlags": 0,
    "ChrModelFlags": 2,
    "Race": 2,
    "Gender": 0,
    "ChrModelId": 3
  },
  "ItemEffects": null,
  "Equipment": {
    "1": 3047,
    "5": 37882,
    "6": 30492,
    "7": 27043,
    "8": 27278,
    "9": 23366
  },
  "ComponentTextures": null,
  "ComponentModels": null,
  "StateKit": null,
  "StateKits": null,
  "Scale": 1
}