{
  "Model": 0,
  "Textures": null,
  "Textures2": null,
  "TextureFiles": {
    "131802": [
      {
        "FileDataId": 1007835,
        "Gender": 3,
        "Class": 0,
        "Race": 0,
        "ExtraData": 0
      }
    ]
  },
  "ModelFiles": null,
  "Item": null,
  "Creature": {
    "CreatureGeosetData": null,
    "CreatureGeosetDataID": 0,
    "CreatureModelAlpha": 255,
    "Texture": 131802,
    "CreatureCustomizations": [
      {
        "optionId": 128,
        "choiceId": 18038
      },
      {
        "optionId": 129,
        "choiceId": 18042
      },
      {
        "optionId": 130,
        "choiceId": 18055
      },
      {
        "optionId": 131,
        "choiceId": 18063
      },
      {
        "optionId": 132,
        "choiceId": 18068
      }
    ],
    "ParticleColor": null
  },
  "Character": {
    "RaceFlags": 0,
    "ChrModelFlags": 3,
    "Race": 11,
    "Gender": 0,
    "ChrModelId": 21
  },
  "ItemEffects": null,
  "Equipment": {
    "5": 36124,
    "6": 36119,
    "7": 36125,
    "8": 36126,
    "9": 4462
  },
  "ComponentTextures": null,
  "ComponentModels": null,
  "StateKit": null,
  "StateKits": null,
  "Scale": 1
}