{
  "Model": 0,
  "Textures": null,
  "Textures2": null,
  "TextureFiles": {
    "211129": [
      {
        "FileDataId": 1104666,
        "Gender": 3,
        "Class": 0,
        "Race": 0,
        "ExtraData": 0
      }
    ]
  },
  "ModelFiles": null,
  "Item": null,
  "Creature": {
    "CreatureGeosetData": null,
    "CreatureGeosetDataID": 0,
    "CreatureModelAlpha": 255,
    "Texture": 211129,
    "CreatureCustomizations": [
      {
        "optionId": 119,
        "choiceId": 17966
      },
      {
        "optionId": 120,
        "choiceId": 17979
      },
      {
        "optionId": 121,
        "choiceId": 18002
      },
      {
        "optionId": 122,
        "choiceId": 18013
      },
      {
        "optionId": 123,
        "choiceId": 18014
      }
    ],
    "ParticleColor": null
  },
  "Character": {
    "RaceFlags": 0,
    "ChrModelFlags": 2,
    "Race": 10,
    "Gender": 1,
    "ChrModelId": 20
  },
  "ItemEffects": null,
  "Equipment": {
    "1": 43887,
    "3": 45459,
    "4": 5345,
    "5": 35081,
    "6": 34699,
    "7": 34687,
    "8": 34684,
    "10": 40024,
    "19": 44852
  },
  "ComponentTextures": null,
  "ComponentModels": null,
  "StateKit": null,
  "StateKits": null,
  "Scale": 1
}