{
  "Model": 0,
  "Textures": null,
  "Textures2": null,
  "TextureFiles": {
    "130308": [
      {
        "FileDataId": 570219,
        "Gender": 3,
        "Class": 0,
        "Race": 0,
        "ExtraData": 0
      }
    ]
  },
  "ModelFiles": null,
  "Item": null,
  "Creature": {
    "CreatureGeosetData": null,
    "CreatureGeosetDataID": 0,
    "CreatureModelAlpha": 255,
    "Texture": 130308,
    "CreatureCustomizations": [
      {
        "optionId": 49,
        "choiceId": 17525
      },
      {
        "optionId": 50,
        "choiceId": 17534
      },
      {
        "optionId": 51,
        "choiceId": 17544
      },
      {
        "optionId": 52,
        "choiceId": 17549
      },
      {
        "optionId": 53,
        "choiceId": 17559
      }
    ],
    "ParticleColor": null
  },
  "Character": {
    "RaceFlags": 0,
    "ChrModelFlags": 0,
    "Race": 4,
    "Gender": 1,
    "ChrModelId": 8
  },
  "ItemEffects": null,
  "Equipment": {
    "3": 4491,
    "5": 8310,
    "6": 5478,
    "7": 5479,
    "8": 3710
  },
  "ComponentTextures": null,
  "ComponentModels": null,
  "StateKit": null,
  "StateKits": null,
  "Scale": 1
}