{
  "Model": 0,
  "Textures": null,
  "Textures2": null,
  "TextureFiles": {
    "190662": [
      {
        "FileDataId": 176124,
        "Gender": 3,
        "Class": 0,
        "Race": 0,
        "ExtraData": 0
      }
    ]
  },
  "ModelFiles": null,
  "Item": null,
  "Creature": {
    "CreatureGeosetData": null,
    "CreatureGeosetDataID": 0,
    "CreatureModelAlpha": 255,
    "Texture": 190662,
    "CreatureCustomizations": [
      {
        "optionId": 58,
        "choiceId": 17566
      },
      {
        "optionId": 59,
        "choiceId": 17571
      },
      {
        "optionId": 60,
        "choiceId": 17583
      },
      {
        "optionId": 61,
        "choiceId": 17600
      },
      {
        "optionId": 62,
        "choiceId": 17605
      }
    ],
    "ParticleColor": null
  },
  "Character": {
    "RaceFlags": 0,
    "ChrModelFlags": 2,
    "Race": 5,
    "Gender": 0,
    "ChrModelId": 9
  },
  "ItemEffects": null,
  "Equipment": {
    "5": 38144,
    "6": 1107,
    "7": 14869,
    "8": 3395,
    "10": 2981,
    "16": 46906
  },
  "ComponentTextures": null,
  "ComponentModels": null,
  "StateKit": null,
  "StateKits": null,
  "Scale": 1
}