{
  "Model": 0,
  "Textures": null,
  "Textures2": null,
  "TextureFiles": {
    "174828": [
      {
        "FileDataId": 176874,
        "Gender": 3,
        "Class": 0,
        "Race": 0,
        "ExtraData": 0
      }
    ]
  },
  "ModelFiles": null,
  "Item": null,
  "Creature": {
    "CreatureGeosetData": null,
    "CreatureGeosetDataID": 0,
    "CreatureModelAlpha": 155,
    "Texture": 174828,
    "CreatureCustomizations": [
      {
        "optionId": 40,
        "choiceId": 17486
      },
      {
        "optionId": 41,
        "choiceId": 17492
      },
      {
        "optionId": 42,
        "choiceId": 17504
      },
      {
        "optionId": 43,
        "choiceId": 17512
      },
      {
        "optionId": 44,
        "choiceId": 17517
      }
    ],
    "ParticleColor": null
  },
  "Character": {
    "RaceFlags": 0,
    "ChrModelFlags": 0,
    "Race": 4,
    "Gender": 0,
    "ChrModelId": 7
  },
  "ItemEffects": null,
  "Equipment": {
    "3": 44635,
    "7": 46471
  },
  "ComponentTextures": null,
  "ComponentModels": null,
  "StateKit": null,
  "StateKits": null,
  "Scale": 1
}