{
  "Model": 0,
  "Textures": null,
  "Textures2": null,
  "TextureFiles": {
    "150550": [
      {
        "FileDataId": 253642,
        "Gender": 3,
        "Class": 0,
        "Race": 0,
        "ExtraData": 0
      }
    ]
  },
  "ModelFiles": null,
  "Item": null,
  "Creature": {
    "CreatureGeosetData": null,
    "CreatureGeosetDataID": 0,
    "CreatureModelAlpha": 255,
    "Texture": 150550,
    "CreatureCustomizations": [
      {
        "optionId": 133,
        "choiceId": 18081
      },
      {
        "optionId": 134,
        "choiceId": 18086
      },
      {
        "optionId": 135,
        "choiceId": 28683
      },
      {
        "optionId": 136,
        "choiceId": 18107
      },
      {
        "optionId": 137,
        "choiceId": 18116
      }
    ],
    "ParticleColor": null
  },
  "Character": {
    "RaceFlags": 0,
    "ChrModelFlags": 3,
    "Race": 11,
    "Gender": 1,
    "ChrModelId": 22
  },
  "ItemEffects": null,
  "Equipment": {
    "3": 50107,
    "5": 58218,
    "6": 36832,
    "7": 40562,
    "10": 9882
  },
  "ComponentTextures": null,
  "ComponentModels": null,
  "StateKit": null,
  "StateKits": null,
  "Scale": 1
}