{
  "Model": 0,
  "Textures": null,
  "Textures2": null,
  "TextureFiles": {
    "150556": [
      {
        "FileDataId": 253657,
        "Gender": 3,
        "Class": 0,
        "Race": 0,
        "ExtraData": 0
      }
    ]
  },
  "ModelFiles": null,
  "Item": null,
  "Creature": {
    "CreatureGeosetData": null,
    "CreatureGeosetDataID": 0,
    "CreatureModelAlpha": 255,
    "Texture": 150556,
    "CreatureCustomizations": [
      {
        "optionId": 133,
        "choiceId": 18076
      },
      {
        "optionId": 134,
        "choiceId": 18085
      },
      {
        "optionId": 135,
        "choiceId": 18101
      },
      {
        "optionId": 136,
        "choiceId": 18109
      },
      {
        "optionId": 137,
        "choiceId": 18116
      }
    ],
    "ParticleColor": null
  },
  "Character": {
    "RaceFlags": 0,
    "ChrModelFlags": 3,
    "Race": 11,
    "Gender": 1,
    "ChrModelId": 22
  },
  "ItemEffects": null,
  "Equipment": {
    "4": 58350,
    "5": 43054,
    "6": 43045,
    "7": 43055,
    "8": 58351,
    "9": 50402,
    "10": 43052,
    "19": 53941
  },
  "ComponentTextures": null,
  "ComponentModels": null,
  "StateKit": null,
  "StateKits": null,
  "Scale": 1
}