{
  "Model": 0,
  "Textures": null,
  "Textures2": null,
  "TextureFiles": {
    "171109": [
      {
        "FileDataId": 315370,
        "Gender": 3,
        "Class": 0,
        "Race": 0,
        "ExtraData": 0
      }
    ]
  },
  "ModelFiles": null,
  "Item": null,
  "Creature": {
    "CreatureGeosetData": null,
    "CreatureGeosetDataID": 0,
    "CreatureModelAlpha": 255,
    "Texture": 171109,
    "CreatureCustomizations": [
      {
        "optionId": 19,
        "choiceId": 28356
      },
      {
        "optionId": 20,
        "choiceId": 28362
      },
      {
        "optionId": 21,
        "choiceId": 17302
      },
      {
        "optionId": 22,
        "choiceId": 17309
      },
      {
        "optionId": 23,
        "choiceId": 17317
      }
    ],
    "ParticleColor": null
  },
  "Character": {
    "RaceFlags": 0,
    "ChrModelFlags": 2,
    "Race": 2,
    "Gender": 0,
    "ChrModelId": 3
  },
  "ItemEffects": null,
  "Equipment": {
    "1": 61157,
    "3": 53583,
    "4": 55065,
    "5": 55066,
    "6": 55067,
    "7": 55068,
    "8": 55069,
    "9": 55070,
    "10": 55071
  },
  "ComponentTextures": null,
  "ComponentModels": null,
  "StateKit": null,
  "StateKits": null,
  "Scale": 1
}