{
  "Model": 0,
  "Textures": null,
  "Textures2": null,
  "TextureFiles": {
    "168126": [
      {
        "FileDataId": 1052420,
        "Gender": 3,
        "Class": 0,
        "Race": 0,
        "ExtraData": 0
      }
    ]
  },
  "ModelFiles": null,
  "Item": null,
  "Creature": {
    "CreatureGeosetData": null,
    "CreatureGeosetDataID": 0,
    "CreatureModelAlpha": 255,
    "Texture": 168126,
    "CreatureCustomizations": [
      {
        "optionId": 9,
        "choiceId": 17169
      },
      {
        "optionId": 10,
        "choiceId": 17179
      },
      {
        "optionId": 11,
        "choiceId": 17184
      },
      {
        "optionId": 12,
        "choiceId": 17196
      },
      {
        "optionId": 13,
        "choiceId": 17210
      }
    ],
    "ParticleColor": null
  },
  "Character": {
    "RaceFlags": 0,
    "ChrModelFlags": 2,
    "Race": 1,
    "Gender": 0,
    "ChrModelId": 1
  },
  "ItemEffects": null,
  "Equipment": {
    "1": 9315,
    "4": 5729,
    "6": 4099,
    "7": 1818,
    "8": 9764,
    "10": 9765
  },
  "ComponentTextures": null,
  "ComponentModels": null,
  "StateKit": null,
  "StateKits": null,
  "Scale": 1
}