{
  "Model": 0,
  "Textures": null,
  "Textures2": null,
  "TextureFiles": {
    "132924": [
      {
        "FileDataId": 1008893,
        "Gender": 3,
        "Class": 0,
        "Race": 0,
        "ExtraData": 0
      }
    ]
  },
  "ModelFiles": null,
  "Item": null,
  "Creature": {
    "CreatureGeosetData": null,
    "CreatureGeosetDataID": 0,
    "CreatureModelAlpha": 128,
    "Texture": 132924,
    "CreatureCustomizations": [
      {
        "optionId": 14,
        "choiceId": 17216
      },
      {
        "optionId": 15,
        "choiceId": 17232
      },
      {
        "optionId": 16,
        "choiceId": 17242
      },
      {
        "optionId": 17,
        "choiceId": 17261
      },
      {
        "optionId": 18,
        "choiceId": 17271
      }
    ],
    "ParticleColor": null
  },
  "Character": {
    "RaceFlags": 0,
    "ChrModelFlags": 2,
    "Race": 1,
    "Gender": 1,
    "ChrModelId": 2
  },
  "ItemEffects": null,
  "Equipment": {
    "1": 15284,
    "4": 11758,
    "7": 11759,
    "8": 15450
  },
  "ComponentTextures": null,
  "ComponentModels": null,
  "StateKit": null,
  "StateKits": null,
  "Scale": 1
}