{
  "Model": 0,
  "Textures": null,
  "Textures2": null,
  "TextureFiles": {
    "158894": [
      {
        "FileDataId": 1040796,
        "Gender": 3,
        "Class": 0,
        "Race": 0,
        "ExtraData": 0
      }
    ]
  },
  "ModelFiles": null,
  "Item": null,
  "Creature": {
    "CreatureGeosetData": null,
    "CreatureGeosetDataID": 0,
    "CreatureModelAlpha": 128,
    "Texture": 158894,
    "CreatureCustomizations": [
      {
        "optionId": 90,
        "choiceId": 17818
      },
      {
        "optionId": 91,
        "choiceId": 17824
      },
      {
        "optionId": 92,
        "choiceId": 17833
      },
      {
        "optionId": 93,
        "choiceId": 17838
      },
      {
        "optionId": 94,
        "choiceId": 17851
      }
    ],
    "ParticleColor": null
  },
  "Character": {
    "RaceFlags": 0,
    "ChrModelFlags": 3,
    "Race": 8,
    "Gender": 0,
    "ChrModelId": 15
  },
  "ItemEffects": null,
  "Equipment": {
    "4": 9177,
    "5": 16007,
    "7": 17705,
    "8": 5606,
    "9": 3630,
    "10": 17707
  },
  "ComponentTextures": null,
  "ComponentModels": null,
  "StateKit": null,
  "StateKits": null,
  "Scale": 1
}