{
  "Model": 0,
  "Textures": null,
  "Textures2": null,
  "TextureFiles": {
    "24954": [
      {
        "FileDataId": 151213,
        "Gender": 3,
        "Class": 0,
        "Race": 0,
        "ExtraData": 0
      }
    ],
    "26357": [
      {
        "FileDataId": 148793,
        "Gender": 3,
        "Class": 0,
        "Race": 0,
        "ExtraData": 0
      }
    ],
    "44643": [
      {
        "FileDataId": 162822,
        "Gender": 1,
        "Class": 0,
        "Race": 0,
        "ExtraData": 0
      },
      {
        "FileDataId": 162823,
        "Gender": 0,
        "Class": 0,
        "Race": 0,
        "ExtraData": 0
      }
    ],
    "34297": [
      {
        "FileDataId": 160171,
        "Gender": 1,
        "Class": 0,
        "Race": 0,
        "ExtraData": 0
      },
      {
        "FileDataId": 160172,
        "Gender": 0,
        "Class": 0,
        "Race": 0,
        "ExtraData": 0
      }
    ]
  },
  "ModelFiles": null,
  "Item": {
    "Flags": 0,
    "InventoryType": 4,
    "ItemClass": 0,
    "ItemSubClass": 0,
    "HideGeosetMale": null,
    "HideGeosetFemale": null,
    "GeosetGroup": [
      1,
      0,
      0,
      0,
      0,
      0
    ],
    "AttachGeosetGroup": [
      0,
      0,
      0,
      0,
      0,
      0
    ],
    "GeosetGroupOverride": 0,
    "ItemVisual": 0,
    "ParticleColor": null
  },
  "Creature": null,
  "Character": null,
  "ItemEffects": null,
  "Equipment": null,
  "ComponentTextures": {
    "0": 24954,
    "1": 26357,
    "3": 44643,
    "4": 34297
  },
  "ComponentModels": null,
  "StateKit": null,
  "StateKits": null,
  "Scale": 1
}