{
  "Model": 0,
  "Textures": null,
  "Textures2": null,
  "TextureFiles": {
    "60463": [
      {
        "FileDataId": 239307,
        "Gender": 3,
        "Class": 0,
        "Race": 0,
        "ExtraData": 0
      }
    ],
    "57104": [
      {
        "FileDataId": 239068,
        "Gender": 3,
        "Class": 0,
        "Race": 0,
        "ExtraData": 0
      }
    ],
    "59354": [
      {
        "FileDataId": 240609,
        "Gender": 1,
        "Class": 0,
        "Race": 0,
        "ExtraData": 0
      },
      {
        "FileDataId": 240610,
        "Gender": 0,
        "Class": 0,
        "Race": 0,
        "ExtraData": 0
      }
    ],
    "56403": [
      {
        "FileDataId": 240299,
        "Gender": 1,
        "Class": 0,
        "Race": 0,
        "ExtraData": 0
      },
      {
        "FileDataId": 240300,
        "Gender": 0,
        "Class": 0,
        "Race": 0,
        "ExtraData": 0
      }
    ],
    "58984": [
      {
        "FileDataId": 240005,
        "Gender": 3,
        "Class": 0,
        "Race": 0,
        "ExtraData": 0
      }
    ]
  },
  "ModelFiles": null,
  "Item": {
    "Flags": 0,
    "InventoryType": 4,
    "ItemClass": 0,
    "ItemSubClass": 0,
    "HideGeosetMale": null,
    "HideGeosetFemale": null,
    "GeosetGroup": [
      0,
      0,
      0,
      0,
      0,
      0
    ],
    "AttachGeosetGroup": [
      0,
      0,
      0,
      0,
      0,
      0
    ],
    "GeosetGroupOverride": 0,
    "ItemVisual": 0,
    "ParticleColor": null
  },
  "Creature": null,
  "Character": null,
  "ItemEffects": null,
  "Equipment": null,
  "ComponentTextures": {
    "0": 60463,
    "1": 57104,
    "3": 59354,
    "4": 56403,
    "5": 58984
  },
  "ComponentModels": null,
  "StateKit": null,
  "StateKits": null,
  "Scale": 1
}