{
  "Model": 0,
  "Textures": null,
  "Textures2": null,
  "TextureFiles": {
    "61858": [
      {
        "FileDataId": 306747,
        "Gender": 3,
        "Class": 0,
        "Race": 0,
        "ExtraData": 0
      }
    ],
    "61857": [
      {
        "FileDataId": 306746,
        "Gender": 3,
        "Class": 0,
        "Race": 0,
        "ExtraData": 0
      }
    ],
    "61901": [
      {
        "FileDataId": 306758,
        "Gender": 1,
        "Class": 0,
        "Race": 0,
        "ExtraData": 0
      },
      {
        "FileDataId": 306759,
        "Gender": 0,
        "Class": 0,
        "Race": 0,
        "ExtraData": 0
      }
    ],
    "61900": [
      {
        "FileDataId": 306756,
        "Gender": 1,
        "Class": 0,
        "Race": 0,
        "ExtraData": 0
      },
      {
        "FileDataId": 306757,
        "Gender": 0,
        "Class": 0,
        "Race": 0,
        "ExtraData": 0
      }
    ],
    "61899": [
      {
        "FileDataId": 306755,
        "Gender": 3,
        "Class": 0,
        "Race": 0,
        "ExtraData": 0
      }
    ],
    "61896": [
      {
        "FileDataId": 306752,
        "Gender": 3,
        "Class": 0,
        "Race": 0,
        "ExtraData": 0
      }
    ]
  },
  "ModelFiles": null,
  "Item": {
    "Flags": 0,
    "InventoryType": 20,
    "ItemClass": 4,
    "ItemSubClass": 3,
    "HideGeosetMale": null,
    "HideGeosetFemale": null,
    "GeosetGroup": [
      0,
      0,
      1,
      0,
      0,
      0
    ],
    "AttachGeosetGroup": [
      0,
      0,
      0,
      0,
      0,
      0
    ],
    "GeosetGroupOverride": 0,
    "ItemVisual": 0,
    "ParticleColor": null
  },
  "Creature": null,
  "Character": null,
  "ItemEffects": null,
  "Equipment": null,
  "ComponentTextures": {
    "0": 61858,
    "1": 61857,
    "3": 61901,
    "4": 61900,
    "5": 61899,
    "6": 61896
  },
  "ComponentModels": null,
  "StateKit": null,
  "StateKits": null,
  "Scale": 1
}