{
  "Model": 0,
  "Textures": null,
  "Textures2": null,
  "TextureFiles": {
    "30397": [
      {
        "FileDataId": 152470,
        "Gender": 3,
        "Class": 0,
        "Race": 0,
        "ExtraData": 0
      }
    ],
    "26543": [
      {
        "FileDataId": 150807,
        "Gender": 3,
        "Class": 0,
        "Race": 0,
        "ExtraData": 0
      }
    ],
    "45257": [
      {
        "FileDataId": 164965,
        "Gender": 1,
        "Class": 0,
        "Race": 0,
        "ExtraData": 0
      },
      {
        "FileDataId": 164966,
        "Gender": 0,
        "Class": 0,
        "Race": 0,
        "ExtraData": 0
      }
    ],
    "44571": [
      {
        "FileDataId": 162268,
        "Gender": 1,
        "Class": 0,
        "Race": 0,
        "ExtraData": 0
      },
      {
        "FileDataId": 162269,
        "Gender": 0,
        "Class": 0,
        "Race": 0,
        "ExtraData": 0
      }
    ],
    "35679": [
      {
        "FileDataId": 159669,
        "Gender": 3,
        "Class": 0,
        "Race": 0,
        "ExtraData": 0
      }
    ],
    "30328": [
      {
        "FileDataId": 156990,
        "Gender": 3,
        "Class": 0,
        "Race": 0,
        "ExtraData": 0
      }
    ]
  },
  "ModelFiles": null,
  "Item": {
    "Flags": 0,
    "InventoryType": 20,
    "ItemClass": 4,
    "ItemSubClass": 1,
    "HideGeosetMale": null,
    "HideGeosetFemale": null,
    "GeosetGroup": [
      1,
      0,
      1,
      0,
      0,
      0
    ],
    "AttachGeosetGroup": [
      0,
      0,
      0,
      0,
      0,
      0
    ],
    "GeosetGroupOverride": 0,
    "ItemVisual": 0,
    "ParticleColor": null
  },
  "Creature": null,
  "Character": null,
  "ItemEffects": null,
  "Equipment": null,
  "ComponentTextures": {
    "0": 30397,
    "1": 26543,
    "3": 45257,
    "4": 44571,
    "5": 35679,
    "6": 30328
  },
  "ComponentModels": null,
  "StateKit": null,
  "StateKits": null,
  "Scale": 1
}